pymal_basic/__init__.py
pymal_basic/anime.py
pymal_basic/example.py
pymal_basics-0.0.2.dist-info/LICENSE
pymal_basics-0.0.2.dist-info/METADATA
pymal_basics-0.0.2.dist-info/WHEEL
pymal_basics-0.0.2.dist-info/top_level.txt
pymal_basics-0.0.2.dist-info/RECORD
