Metadata-Version: 2.1
Name: pymal_basics
Version: 0.0.2
Summary: Simple library to get Anime title and ID from MyAnimeList
Home-page: https://github.com/KidiXDev/pymal_basic
Author: KidiXDev
Author-email: <kidixdev@gmail.com>
License: MIT
Keywords: mal,myanimelist
Classifier: Development Status :: 1 - Planning
License-File: LICENSE
